authf/__init__.py
authf/add_offline.py
authf/cli.py
authf/encryption.py
authf/engine.py
authf/test_engine.py
authf-0.0.5.dist-info/LICENSE
authf-0.0.5.dist-info/METADATA
authf-0.0.5.dist-info/WHEEL
authf-0.0.5.dist-info/entry_points.txt
authf-0.0.5.dist-info/top_level.txt
authf-0.0.5.dist-info/RECORD
