Metadata-Version: 2.1
Name: authf
Version: 0.0.5
Summary: Authenticator Application
Home-page: https://github.com/1darshanpatil/authf
Author: Darshan P.
License: MIT
Project-URL: Documentation, https://github.com/1darshanpatil/authf#readme
Project-URL: Source, https://github.com/1darshanpatil/authf
Project-URL: Tracker, https://github.com/1darshanpatil/authf/issues
Keywords: authenticator,authentication,Two Step Authentication
Platform: UNKNOWN
Classifier: Development Status :: 4 - Beta
Classifier: Programming Language :: Python :: 3
Classifier: License :: OSI Approved :: MIT License
Classifier: Operating System :: OS Independent
Requires-Python: >=3.6
License-File: LICENSE
Requires-Dist: cffi==1.17.1
Requires-Dist: cryptography==45.0.5
Requires-Dist: pycparser==2.22
Requires-Dist: pyotp==2.9.0
Requires-Dist: pyperclip==1.8.2
